Metadata-Version: 1.1
Name: kitovu
Version: 0.1.0
Summary: OpenHSR Connect 2
Home-page: https://github.com/kitovu-bot/kitovu
Author: Méline Sieber, Nicolas Ganz, Florian Bruhin
Author-email: kitovu@the-compiler.org
License: GPLv3
Platform: UNKNOWN
Classifier: Development Status :: 2 - Pre-Alpha
Classifier: Intended Audience :: Education
Classifier: License :: OSI Approved :: GNU General Public License v3 (GPLv3)
Classifier: Operating System :: Unix
Classifier: Operating System :: POSIX
Classifier: Operating System :: Microsoft :: Windows
Classifier: Programming Language :: Python
Classifier: Programming Language :: Python :: 3.6
Classifier: Programming Language :: Python :: Implementation :: CPython
Classifier: Topic :: Utilities
Classifier: Topic :: Education
